hMailServer/__init__.py
hMailServer/test1.py
hMailServer-0.0.1.dist-info/LICENSE.txt
hMailServer-0.0.1.dist-info/METADATA
hMailServer-0.0.1.dist-info/WHEEL
hMailServer-0.0.1.dist-info/entry_points.txt
hMailServer-0.0.1.dist-info/top_level.txt
hMailServer-0.0.1.dist-info/RECORD
